{
  "generatedAt": "2026-06-28T16:57:22.461Z",
  "stagingBaseUrl": "https://staging.website-production-26u.pages.dev",
  "manifestRoutes": 55,
  "manifestRedirects": 117,
  "capturedRoutes": 55,
  "discoveredRoutes": 0,
  "capturedRedirects": 117,
  "capturedAssets": 131,
  "capturedScreenshots": 110,
  "routeStatusCounts": {
    "200": 55
  },
  "routeClassificationCounts": {
    "migrate-verbatim": 54,
    "special-404-route": 1
  },
  "redirectStatusCounts": {
    "301": 117
  },
  "assetStatusCounts": {
    "200": 131
  },
  "assetExtensionCounts": {
    "js": 2,
    "css": 4,
    "svg": 5,
    "woff2": 1,
    "webp": 119
  },
  "failures": []
}
